udkanbun/__init__.py
udkanbun/cli.py
udkanbun/conllusvgview.js
udkanbun/deprelja.py
udkanbun/kaeriten.py
udkanbun/ud-kanbun.udpipe
udkanbun/udkanbun.py
udkanbun/mecab-kanbun/char.bin
udkanbun/mecab-kanbun/char.def
udkanbun/mecab-kanbun/dicrc
udkanbun/mecab-kanbun/dict.KTp2.csv
udkanbun/mecab-kanbun/dict.gloss.csv
udkanbun/mecab-kanbun/dict.name.csv
udkanbun/mecab-kanbun/dict.symbol.csv
udkanbun/mecab-kanbun/feature.def
udkanbun/mecab-kanbun/left-id.def
udkanbun/mecab-kanbun/matrix.bin
udkanbun/mecab-kanbun/matrix.def
udkanbun/mecab-kanbun/model.bin
udkanbun/mecab-kanbun/model.def
udkanbun/mecab-kanbun/rewrite.def
udkanbun/mecab-kanbun/right-id.def
udkanbun/mecab-kanbun/sys.dic
udkanbun/mecab-kanbun/unk.def
udkanbun/mecab-kanbun/unk.dic
udkanbun-1.5.3.dist-info/LICENSE.txt
udkanbun-1.5.3.dist-info/METADATA
udkanbun-1.5.3.dist-info/WHEEL
udkanbun-1.5.3.dist-info/entry_points.txt
udkanbun-1.5.3.dist-info/top_level.txt
udkanbun-1.5.3.dist-info/RECORD
