Metadata-Version: 2.1
Name: udkanbun
Version: 1.5.3
Summary: Tokenizer POS-tagger and Dependency-parser for Classical Chinese
Home-page: https://github.com/KoichiYasuoka/UD-Kanbun
Author: Koichi Yasuoka
Author-email: yasuoka@kanji.zinbun.kyoto-u.ac.jp
License: MIT
Project-URL: ud-kanbun, https://corpus.kanji.zinbun.kyoto-u.ac.jp/gitlab/Kanbun/ud-kanbun
Project-URL: Source, https://github.com/KoichiYasuoka/UD-Kanbun
Project-URL: Tracker, https://github.com/KoichiYasuoka/UD-Kanbun/issues
Keywords: udpipe mecab nlp
Platform: UNKNOWN
Classifier: License :: OSI Approved :: MIT License
Classifier: Programming Language :: Python :: 3
Classifier: Operating System :: OS Independent
Classifier: Topic :: Text Processing :: Linguistic
Requires-Python: >=3.6
Requires-Dist: ufal.udpipe (>=1.2.0)
Requires-Dist: mecab-python3 (>=0.996)
